{ "columns":22,
 "image":"swamp_.png",
 "imageheight":144,
 "imagewidth":352,
 "margin":0,
 "name":"swamp_",
 "spacing":0,
 "tilecount":198,
 "tiledversion":"1.9.1",
 "tileheight":16,
 "tiles":[
        {
         "id":111,
         "objectgroup":
            {
             "draworder":"index",
             "id":2,
             "name":"",
             "objects":[
                    {
                     "class":"",
                     "height":5.1304347826087,
                     "id":1,
                     "name":"",
                     "rotation":0,
                     "visible":true,
                     "width":6.78260869565217,
                     "x":9.21739130434783,
                     "y":9.30434782608696
                    }, 
                    {
                     "class":"",
                     "height":1.69565217391304,
                     "id":2,
                     "name":"",
                     "rotation":0,
                     "visible":true,
                     "width":3.04347826086956,
                     "x":9,
                     "y":14.4347826086957
                    }],
             "opacity":1,
             "type":"objectgroup",
             "visible":true,
             "x":0,
             "y":0
            }
        }, 
        {
         "id":112,
         "objectgroup":
            {
             "draworder":"index",
             "id":2,
             "name":"",
             "objects":[
                    {
                     "class":"",
                     "height":4.17391304347826,
                     "id":1,
                     "name":"",
                     "rotation":0,
                     "visible":true,
                     "width":15.9565217391304,
                     "x":0,
                     "y":8.82608695652174
                    }],
             "opacity":1,
             "type":"objectgroup",
             "visible":true,
             "x":0,
             "y":0
            }
        }, 
        {
         "id":113,
         "objectgroup":
            {
             "draworder":"index",
             "id":2,
             "name":"",
             "objects":[
                    {
                     "class":"",
                     "height":5.1304347826087,
                     "id":1,
                     "name":"",
                     "rotation":0,
                     "visible":true,
                     "width":6.91304347826087,
                     "x":0.0434782608695652,
                     "y":8.82608695652174
                    }, 
                    {
                     "class":"",
                     "height":2.08695652173913,
                     "id":2,
                     "name":"",
                     "rotation":0,
                     "visible":true,
                     "width":3.1304347826087,
                     "x":3.8695652173913,
                     "y":13.9130434782609
                    }],
             "opacity":1,
             "type":"objectgroup",
             "visible":true,
             "x":0,
             "y":0
            }
        }, 
        {
         "id":114,
         "objectgroup":
            {
             "draworder":"index",
             "id":2,
             "name":"",
             "objects":[
                    {
                     "class":"",
                     "height":9.04347826086956,
                     "id":1,
                     "name":"",
                     "rotation":0,
                     "visible":true,
                     "width":13.0434782608696,
                     "x":2.91304347826087,
                     "y":3
                    }, 
                    {
                     "class":"",
                     "height":3.95652173913044,
                     "id":2,
                     "name":"",
                     "rotation":0,
                     "visible":true,
                     "width":4.08695652173913,
                     "x":2.8695652173913,
                     "y":12.0434782608696
                    }],
             "opacity":1,
             "type":"objectgroup",
             "visible":true,
             "x":0,
             "y":0
            }
        }, 
        {
         "id":115,
         "objectgroup":
            {
             "draworder":"index",
             "id":2,
             "name":"",
             "objects":[
                    {
                     "class":"",
                     "height":8.91304347826087,
                     "id":1,
                     "name":"",
                     "rotation":0,
                     "visible":true,
                     "width":12.9565217391304,
                     "x":0.0869565217391304,
                     "y":3.08695652173913
                    }, 
                    {
                     "class":"",
                     "height":4.04347826086957,
                     "id":2,
                     "name":"",
                     "rotation":0,
                     "visible":true,
                     "width":4.17391304347826,
                     "x":8.82608695652174,
                     "y":11.9565217391304
                    }],
             "opacity":1,
             "type":"objectgroup",
             "visible":true,
             "x":0,
             "y":0
            }
        }, 
        {
         "id":119,
         "objectgroup":
            {
             "draworder":"index",
             "id":2,
             "name":"",
             "objects":[
                    {
                     "class":"",
                     "height":7.73913043478261,
                     "id":1,
                     "name":"",
                     "rotation":0,
                     "visible":true,
                     "width":12.9130434782609,
                     "x":3,
                     "y":3
                    }, 
                    {
                     "class":"",
                     "height":5.17391304347826,
                     "id":2,
                     "name":"",
                     "rotation":0,
                     "visible":true,
                     "width":3.95652173913043,
                     "x":3,
                     "y":10.8260869565217
                    }],
             "opacity":1,
             "type":"objectgroup",
             "visible":true,
             "x":0,
             "y":0
            }
        }, 
        {
         "id":120,
         "objectgroup":
            {
             "draworder":"index",
             "id":2,
             "name":"",
             "objects":[
                    {
                     "class":"",
                     "height":7.95652173913044,
                     "id":1,
                     "name":"",
                     "rotation":0,
                     "visible":true,
                     "width":12.9130434782609,
                     "x":0,
                     "y":3.04347826086956
                    }, 
                    {
                     "class":"",
                     "height":4.95652173913043,
                     "id":2,
                     "name":"",
                     "rotation":0,
                     "visible":true,
                     "width":3.95652173913043,
                     "x":9,
                     "y":11
                    }],
             "opacity":1,
             "type":"objectgroup",
             "visible":true,
             "x":0,
             "y":0
            }
        }, 
        {
         "id":133,
         "objectgroup":
            {
             "draworder":"index",
             "id":2,
             "name":"",
             "objects":[
                    {
                     "class":"",
                     "height":16.1739130434783,
                     "id":1,
                     "name":"",
                     "rotation":0,
                     "visible":true,
                     "width":4.26086956521739,
                     "x":8.91304347826087,
                     "y":-0.173913043478261
                    }],
             "opacity":1,
             "type":"objectgroup",
             "visible":true,
             "x":0,
             "y":0
            }
        }, 
        {
         "id":135,
         "objectgroup":
            {
             "draworder":"index",
             "id":2,
             "name":"",
             "objects":[
                    {
                     "class":"",
                     "height":15.9130434782609,
                     "id":1,
                     "name":"",
                     "rotation":0,
                     "visible":true,
                     "width":4.1304347826087,
                     "x":2.95652173913043,
                     "y":0.0869565217391304
                    }],
             "opacity":1,
             "type":"objectgroup",
             "visible":true,
             "x":0,
             "y":0
            }
        }, 
        {
         "id":136,
         "objectgroup":
            {
             "draworder":"index",
             "id":2,
             "name":"",
             "objects":[
                    {
                     "class":"",
                     "height":12.0434782608696,
                     "id":1,
                     "name":"",
                     "rotation":0,
                     "visible":true,
                     "width":4.34782608695652,
                     "x":2.73913043478261,
                     "y":-0.0869565217391304
                    }, 
                    {
                     "class":"",
                     "height":3.26086956521739,
                     "id":2,
                     "name":"",
                     "rotation":0,
                     "visible":true,
                     "width":8.8695652173913,
                     "x":7.1304347826087,
                     "y":8.78260869565217
                    }],
             "opacity":1,
             "type":"objectgroup",
             "visible":true,
             "x":0,
             "y":0
            }
        }, 
        {
         "id":137,
         "objectgroup":
            {
             "draworder":"index",
             "id":2,
             "name":"",
             "objects":[
                    {
                     "class":"",
                     "height":13.0434782608696,
                     "id":1,
                     "name":"",
                     "rotation":0,
                     "visible":true,
                     "width":4.26086956521739,
                     "x":8.82608695652174,
                     "y":0.0434782608695652
                    }, 
                    {
                     "class":"",
                     "height":4.08695652173913,
                     "id":2,
                     "name":"",
                     "rotation":0,
                     "visible":true,
                     "width":8.69565217391304,
                     "x":0.130434782608696,
                     "y":8.8695652173913
                    }],
             "opacity":1,
             "type":"objectgroup",
             "visible":true,
             "x":0,
             "y":0
            }
        }, 
        {
         "id":141,
         "objectgroup":
            {
             "draworder":"index",
             "id":2,
             "name":"",
             "objects":[
                    {
                     "class":"",
                     "height":12.9565217391304,
                     "id":1,
                     "name":"",
                     "rotation":0,
                     "visible":true,
                     "width":7,
                     "x":2.95652173913043,
                     "y":0
                    }, 
                    {
                     "class":"",
                     "height":4.08695652173913,
                     "id":2,
                     "name":"",
                     "rotation":0,
                     "visible":true,
                     "width":5.95652173913044,
                     "x":10.0434782608696,
                     "y":8.8695652173913
                    }],
             "opacity":1,
             "type":"objectgroup",
             "visible":true,
             "x":0,
             "y":0
            }
        }, 
        {
         "id":142,
         "objectgroup":
            {
             "draworder":"index",
             "id":2,
             "name":"",
             "objects":[
                    {
                     "class":"",
                     "height":13.1304347826087,
                     "id":1,
                     "name":"",
                     "rotation":0,
                     "visible":true,
                     "width":3.95652173913044,
                     "x":8.95652173913043,
                     "y":-0.217391304347826
                    }, 
                    {
                     "class":"",
                     "height":4.1304347826087,
                     "id":2,
                     "name":"",
                     "rotation":0,
                     "visible":true,
                     "width":8.69565217391304,
                     "x":0.0869565217391304,
                     "y":8.8695652173913
                    }],
             "opacity":1,
             "type":"objectgroup",
             "visible":true,
             "x":0,
             "y":0
            }
        }, 
        {
         "id":155,
         "objectgroup":
            {
             "draworder":"index",
             "id":2,
             "name":"",
             "objects":[
                    {
                     "class":"",
                     "height":12,
                     "id":1,
                     "name":"",
                     "rotation":0,
                     "visible":true,
                     "width":3,
                     "x":9.04347826086956,
                     "y":0
                    }, 
                    {
                     "class":"",
                     "height":5.95652173913043,
                     "id":2,
                     "name":"",
                     "rotation":0,
                     "visible":true,
                     "width":3.82608695652174,
                     "x":12.1739130434783,
                     "y":5.95652173913043
                    }],
             "opacity":1,
             "type":"objectgroup",
             "visible":true,
             "x":0,
             "y":0
            }
        }, 
        {
         "id":156,
         "objectgroup":
            {
             "draworder":"index",
             "id":2,
             "name":"",
             "objects":[
                    {
                     "class":"",
                     "height":8.78260869565217,
                     "id":1,
                     "name":"",
                     "rotation":0,
                     "visible":true,
                     "width":15.8695652173913,
                     "x":0.130434782608696,
                     "y":3.17391304347826
                    }],
             "opacity":1,
             "type":"objectgroup",
             "visible":true,
             "x":0,
             "y":0
            }
        }, 
        {
         "id":157,
         "objectgroup":
            {
             "draworder":"index",
             "id":2,
             "name":"",
             "objects":[
                    {
                     "class":"",
                     "height":11.8260869565217,
                     "id":1,
                     "name":"",
                     "rotation":0,
                     "visible":true,
                     "width":3.91304347826087,
                     "x":3.04347826086956,
                     "y":0.130434782608696
                    }, 
                    {
                     "class":"",
                     "height":7.91304347826087,
                     "id":2,
                     "name":"",
                     "rotation":0,
                     "visible":true,
                     "width":3,
                     "x":-0.0869565217391304,
                     "y":4
                    }],
             "opacity":1,
             "type":"objectgroup",
             "visible":true,
             "x":0,
             "y":0
            }
        }],
 "tilewidth":16,
 "type":"tileset",
 "version":"1.8"
}